mrjet/__init__.py
mrjet/browser_func.py
mrjet/cli.py
mrjet/downloader.py
mrjet/logger.py
mrjet/request_handler.py
mrjet-0.1.3.dist-info/licenses/LICENSE
mrjet-0.1.3.dist-info/METADATA
mrjet-0.1.3.dist-info/WHEEL
mrjet-0.1.3.dist-info/entry_points.txt
mrjet-0.1.3.dist-info/top_level.txt
mrjet-0.1.3.dist-info/RECORD
