Metadata-Version: 2.4
Name: mrjet
Version: 0.1.3
Summary: simple m3u8 downloader for missav
Author: cailurus
Project-URL: Homepage, https://github.com/cailurus/mrjet
Classifier: Programming Language :: Python :: 3
Classifier: License :: OSI Approved :: MIT License
Classifier: Operating System :: OS Independent
Requires-Python: >=3.10
License-File: LICENSE
Requires-Dist: curl-cffi>=0.9.0
Requires-Dist: m3u8>=6.0.0
Requires-Dist: pym3u8downloader>=0.1.8
Requires-Dist: requests>=2.32.3
Requires-Dist: patchright>=1.51.3
Dynamic: license-file
